acqua/__init__.py
acqua/configs.py
acqua/core.py
acqua/schemas.yml
acqua/commands/__init__.py
acqua/commands/auth.py
acqua/commands/build.py
acqua/commands/clean.py
acqua/commands/dashboard.py
acqua/commands/deploy.py
acqua/commands/pull.py
acqua/inlets/__init__.py
acqua/inlets/estuary.py
acqua/inlets/fjord.py
acqua/inlets/lagoon.py
acqua/types/__init__.py
acqua/types/blockchain_info.py
acqua/types/build.py
acqua/types/chain.py
acqua/types/difficulty_adjustment.py
acqua/types/mempool_info.py
acqua/types/service.py
acqua-0.2.1.dist-info/METADATA
acqua-0.2.1.dist-info/WHEEL
acqua-0.2.1.dist-info/entry_points.txt
acqua-0.2.1.dist-info/licenses/LICENSE
acqua-0.2.1.dist-info/RECORD
